aimaestro/__init__.py
aimaestro/abcglobal/__init__.py
aimaestro/abcglobal/global_var.py
aimaestro/abcglobal/key.py
aimaestro/aiagent/__init__.py
aimaestro/aiagent/_openai.py
aimaestro/management/__init__.py
aimaestro/management/management.py
aimaestro/management/dist/index.html
aimaestro/management/dist/assets/arco.2329baeb.js
aimaestro/management/dist/assets/arco.2329baeb.js.gz
aimaestro/management/dist/assets/chart.db8aed57.js
aimaestro/management/dist/assets/chart.db8aed57.js.gz
aimaestro/management/dist/assets/default-layout.9001d833.js
aimaestro/management/dist/assets/default-layout.9001d833.js.gz
aimaestro/management/dist/assets/default-layout.d25ce522.css
aimaestro/management/dist/assets/default-layout.d25ce522.css.gz
aimaestro/management/dist/assets/favicon.01719bfc.ico
aimaestro/management/dist/assets/home-layout.c9e78626.js
aimaestro/management/dist/assets/home-layout.c9e78626.js.gz
aimaestro/management/dist/assets/home-layout.d911a8a2.css
aimaestro/management/dist/assets/home-layout.d911a8a2.css.gz
aimaestro/management/dist/assets/index.13b2512e.js
aimaestro/management/dist/assets/index.143c312c.css
aimaestro/management/dist/assets/index.143c312c.css.gz
aimaestro/management/dist/assets/index.167a1896.js
aimaestro/management/dist/assets/index.167a1896.js.gz
aimaestro/management/dist/assets/index.285e7ffc.js
aimaestro/management/dist/assets/index.2a1c99a8.css
aimaestro/management/dist/assets/index.338b4449.css
aimaestro/management/dist/assets/index.338b4449.css.gz
aimaestro/management/dist/assets/index.356ac669.css
aimaestro/management/dist/assets/index.356ac669.css.gz
aimaestro/management/dist/assets/index.3b851811.js
aimaestro/management/dist/assets/index.3b851811.js.gz
aimaestro/management/dist/assets/index.749fce18.css
aimaestro/management/dist/assets/index.75ecdef5.css
aimaestro/management/dist/assets/index.75ecdef5.css.gz
aimaestro/management/dist/assets/index.7c16c0f8.css
aimaestro/management/dist/assets/index.7c16c0f8.css.gz
aimaestro-1.1.8.dist-info/LICENSE
aimaestro-1.1.8.dist-info/METADATA
aimaestro-1.1.8.dist-info/WHEEL
aimaestro-1.1.8.dist-info/top_level.txt
aimaestro-1.1.8.dist-info/RECORD
