Metadata-Version: 2.2
Name: aimaestro
Version: 1.1.8
Summary: aimaestro Description
Home-page: https://github.com/ZYPGITA/aimaestro
Author: YanPing
Author-email: zyphhxx@foxmail.com
Maintainer: YanPing
Maintainer-email: zyphhxx@foxmail.com
License: MIT License
Classifier: Development Status :: 3 - Alpha
Classifier: Intended Audience :: Developers
Classifier: Topic :: Software Development :: Build Tools
Classifier: License :: OSI Approved :: MIT License
Classifier: Programming Language :: Python :: 3
Requires-Python: >=3.8
License-File: LICENSE
Requires-Dist: psutil
Requires-Dist: pika
Requires-Dist: pytz
Requires-Dist: pymongo
Requires-Dist: pyyaml
Requires-Dist: selenium
Requires-Dist: webdriver_manager
Requires-Dist: pycryptodomex
Dynamic: author
Dynamic: author-email
Dynamic: classifier
Dynamic: description
Dynamic: home-page
Dynamic: license
Dynamic: maintainer
Dynamic: maintainer-email
Dynamic: requires-dist
Dynamic: requires-python
Dynamic: summary
